pointpca2/pointpca2.cpython-312-darwin.so
pointpca2/__init__.py
pointpca2-0.5.1.dist-info/RECORD
pointpca2-0.5.1.dist-info/WHEEL
pointpca2-0.5.1.dist-info/METADATA
pointpca2-0.5.1.dist-info/licenses/LICENSE
