Metadata-Version: 2.4
Name: pointpca2
Version: 0.5.1
Requires-Dist: numpy>=1.26
Requires-Dist: toml>=0.10.0
License-File: LICENSE
Summary: A Rust-based Python library for extracting pointpca2 features from Point Clouds.
Requires-Python: >=3.10, <3.13
Project-URL: repository, https://github.com/arthurhscarvalho/pointpca2-pylib
